restic_airflow-0.1.3.dist-info/METADATA
restic_airflow-0.1.3.dist-info/WHEEL
restic_airflow-0.1.3.dist-info/entry_points.txt
restic_airflow-0.1.3.dist-info/licenses/LICENSE
restic_airflow/__init__.py
restic_airflow/helpers.py
restic_airflow/notifications.py
restic_airflow/operators/__init__.py
restic_airflow/operators/restic.py
restic_airflow-0.1.3.dist-info/RECORD
